hex_api/__init__.py
hex_api/auth.py
hex_api/cli.py
hex_api/client.py
hex_api/config.py
hex_api/exceptions.py
hex_api/mcp/__init__.py
hex_api/mcp/config.py
hex_api/mcp/installer.py
hex_api/mcp/server.py
hex_api/resources/__init__.py
hex_api/resources/base.py
hex_api/resources/embedding.py
hex_api/resources/projects.py
hex_api/resources/runs.py
hex_api/resources/semantic_models.py
hex_api-0.1.0.dist-info/METADATA
hex_api-0.1.0.dist-info/WHEEL
hex_api-0.1.0.dist-info/entry_points.txt
hex_api-0.1.0.dist-info/RECORD
