Metadata-Version: 2.4
Name: hex-api
Version: 0.1.0
Summary: Python SDK for the Hex API
Project-URL: Homepage, https://github.com/yourusername/hex-api
Project-URL: Documentation, https://hex-api.readthedocs.io
Project-URL: Repository, https://github.com/yourusername/hex-api
Project-URL: Issues, https://github.com/yourusername/hex-api/issues
Author-email: Franccesco Orozco <franccesco@codingdose.info>
License: MIT
Classifier: Development Status :: 3 - Alpha
Classifier: Intended Audience :: Developers
Classifier: License :: OSI Approved :: MIT License
Classifier: Programming Language :: Python :: 3
Classifier: Programming Language :: Python :: 3.10
Classifier: Programming Language :: Python :: 3.11
Classifier: Programming Language :: Python :: 3.12
Requires-Python: >=3.10
Requires-Dist: httpx>=0.25.0
Requires-Dist: python-dateutil>=2.8.2
Provides-Extra: all
Requires-Dist: fastmcp>=1.0.0; extra == 'all'
Requires-Dist: rich>=13.5.0; extra == 'all'
Requires-Dist: typer>=0.9.0; extra == 'all'
Provides-Extra: cli
Requires-Dist: rich>=13.5.0; extra == 'cli'
Requires-Dist: typer>=0.9.0; extra == 'cli'
Provides-Extra: dev
Requires-Dist: jsonschema>=4.0.0; extra == 'dev'
Requires-Dist: pre-commit>=3.3.0; extra == 'dev'
Requires-Dist: pytest-cov>=4.1.0; extra == 'dev'
Requires-Dist: pytest-mock>=3.11.0; extra == 'dev'
Requires-Dist: pytest>=7.4.0; extra == 'dev'
Requires-Dist: ruff>=0.1.0; extra == 'dev'
Provides-Extra: mcp
Requires-Dist: fastmcp>=1.0.0; extra == 'mcp'
